{"sections":{"main":{"type":"main-collection","blocks":{"d78a5ac3-bb8a-4dc9-b0e6-6235f410682b":{"type":"disruptor","settings":{"devices":"mobile_desktop","autoplay":true,"loop":true,"background_color":"#f8f6f2","apply_overlay":false,"content_position":"middleLeft","subheading":"<p><strong>{{ collection.metafields.custom.sub_title.value }}<\/strong><\/p>","title":"{{ collection.metafields.custom.main_title | metafield_tag }}","description":"{{ collection.metafields.custom.main_description | metafield_tag }}","description_mobile":"{{ collection.metafields.custom.main_description | metafield_tag }}","colour_style":"dark","button_1_text":"","button_1_link":"","button_style":"underline","include_no_media_border":true,"metaobject_autoplay":"","metaobject_loop":"","metaobject_apply_overlay":"","metaobject_content_position":"","metaobject_colour_style":"","metaobject_button_style":""}},"4e25e719-38ed-4409-862b-c0fd0c77bf81":{"type":"disruptor","repeater":"{{ collection.metafields.custom.disrupter_tiles.value }}","settings":{"devices":"mobile_desktop","video":"{{ block.repeater.main_video.value }}","autoplay":true,"loop":true,"image":"{{ block.repeater.main_image.value }}","background_color":"{{ block.repeater.background_colour.value }}","apply_overlay":true,"content_position":"middleLeft","logo_image":"{{ block.repeater.icon.value }}","subheading":"{{ block.repeater.sub_heading | metafield_tag }}","title":"{{ block.repeater.title | metafield_tag }}","description":"{{ block.repeater.description | metafield_tag }}","description_mobile":"","colour_style":"light","button_1_text":"{{ block.repeater.button_1_text.value }}","button_1_link":"{{ block.repeater.button_1_link.value }}","button_style":"underline","include_no_media_border":true,"metaobject_autoplay":"{{ block.repeater.autoplay_video.value }}","metaobject_loop":"{{ block.repeater.loop_video.value }}","metaobject_apply_overlay":"{{ block.repeater.apply_overlay_on_media.value }}","metaobject_content_position":"{{ block.repeater.content_position.value }}","metaobject_colour_style":"{{ block.repeater.colour_style.value }}","metaobject_button_style":"{{ block.repeater.button_style.value }}"}}},"block_order":["d78a5ac3-bb8a-4dc9-b0e6-6235f410682b","4e25e719-38ed-4409-862b-c0fd0c77bf81"],"settings":{"disruptor_tile_positions":"1,9,22,36","show_collection_info":false,"info_devices":"mobile_desktop","show_collection_image":false,"apply_overlay":false,"show_color_swatch":true,"show_vendor":false,"collection_image_size":"normal","show_sort_by":true,"show_layout_switch":true,"show_view_switch":false,"toolbar_position":"top","show_filters":true,"show_filter_color_swatch":true,"expand_filters":false,"filter_position":"sidebar","filter_menu":"","grid_items_per_page":48,"grid_mobile_items_per_row":"2","grid_desktop_items_per_row":3}},"2d6c1f26-8524-4d18-8a1b-e7e4ba45d741":{"type":"styled-with","blocks":{"template--16212444020905__2d6c1f26-8524-4d18-8a1b-e7e4ba45d741-style-1":{"type":"style","repeater":"{{ collection.metafields.custom.style_with_assets.value }}","settings":{"image":"{{ block.repeater.style_with_media.value }}","autoplay":true,"loop":true,"style_tag":"{{ block.repeater.instagram_tag.value }}","link":"{{ block.repeater.style_with_tag_link.value }}","description":"{{ block.repeater.style_with_paragraph | metafield_tag }}","title":"","products":"{{ block.repeater.style_with_product.value }}"}}},"block_order":["template--16212444020905__2d6c1f26-8524-4d18-8a1b-e7e4ba45d741-style-1"],"settings":{"separate_section_with_border":true,"enable_dark":false,"subheading":"","title":"<p>{{ collection.metafields.custom.heading.value }}<\/p>","description":"<p>{{ collection.metafields.custom.description | metafield_tag }}<\/p>","feature_text":"","colour_style":"dark","button_1_text":"","button_1_link":"","button_2_text":"","button_2_link":"","button_style":"underline"}},"5817e914-5d0a-4c53-bb50-7dffd5160a40":{"type":"seo-copy","settings":{"title":"{{ collection.metafields.custom.seo_heading | metafield_tag }}","content_intro":"{{ collection.metafields.custom.seo_intro | metafield_tag }}","content":"{{ collection.metafields.custom.seo_text | metafield_tag }}"}},"88fa601f-3492-4e43-9785-c25d31447025":{"type":"content-list","blocks":{"2996585e-f8d5-4531-b10a-ae93884e894e":{"type":"image","repeater":"{{ collection.metafields.custom.content_section.value }}","settings":{"image":"{{ block.repeater.main_image.value }}","apply_overlay":false,"devices":"mobile_desktop","content_position":"underLeft","subheading":"{{ block.repeater.sub_heading | metafield_tag }}","title":"{{ block.repeater.title | metafield_tag }}","description":"{{ block.repeater.description | metafield_tag }}","description_mobile":"","colour_style":"dark","button_1_text":"{{ block.repeater.button_1_text.value }}","button_1_link":"{{ block.repeater.button_1_link.value }}","button_2_text":"","button_2_link":"","button_style":"underline","include_no_media_border":true,"metaobject_autoplay":"","metaobject_loop":"","metaobject_apply_overlay":"","metaobject_content_position":"","metaobject_colour_style":"","metaobject_button_style":"","metaobject_devices":""}}},"block_order":["2996585e-f8d5-4531-b10a-ae93884e894e"],"settings":{"grid_items_count":3,"grid_items_count_pocket":"1\/2","text_align":"center","subheading":"","title":"","description":"","colour_style":"dark","button_1_text":"","button_1_link":"","button_2_text":"","button_2_link":"","button_style":"underline"}},"1680140665caede3de":{"type":"apps","blocks":{"94efe1bf-95d9-4d43-a08c-65c6afc236da":{"type":"shopify:\/\/apps\/instafeed\/blocks\/app-block\/c447db20-095d-4a10-9725-b5977662c9d5","settings":{"html_area":""}}},"block_order":["94efe1bf-95d9-4d43-a08c-65c6afc236da"],"settings":{"include_margins":true,"subheading":"<p><strong>INSTAGRAM<\/strong><\/p>","title":"<p>Shop our <em>feed<\/em><\/p>","description":"","colour_style":"dark","button_1_text":"","button_1_link":"","button_2_text":"","button_2_link":"","button_style":"underline"}}},"order":["main","2d6c1f26-8524-4d18-8a1b-e7e4ba45d741","5817e914-5d0a-4c53-bb50-7dffd5160a40","88fa601f-3492-4e43-9785-c25d31447025","1680140665caede3de"]}