{"sections":{"text_with_media_jNTCBM":{"type":"text-with-media","name":"Text with media","settings":{"remove_spacing_top":false,"remove_spacing_bottom":false,"enable_newsletter_subscribe":false,"klaviyo_form_id":"","media_position":"right","media_position_mobile":"bottom","media_width":"7","content_position":"middleLeft","subheading":"<p>WIn A $500 gift voucher<\/p>","title":"<p>Enter To Win<\/p>","description":"<p>Sign up to our mailing list and enter the draw for your chance to win.<\/p><p><\/p>","colour_style":"dark","button_1_text":"","button_1_link":"","button_style":"underline"}},"17648044152b9d9144":{"type":"apps","blocks":{"klaviyo_email_marketing_sms_form_embed_block_9ngdMB":{"type":"shopify:\/\/apps\/klaviyo-email-marketing-sms\/blocks\/form-embed-block\/2632fe16-c075-4321-a88b-50b567f42507","settings":{"formId":"S2gUx9"}}},"block_order":["klaviyo_email_marketing_sms_form_embed_block_9ngdMB"],"disabled":true,"settings":{"include_margins":true,"subheading":"","title":"","description":"","colour_style":"dark","button_1_text":"","button_1_link":"","button_2_text":"","button_2_link":"","button_style":"underline"}},"main":{"type":"main-page","settings":{"subheading":"<p><strong>{{ page.metafields.custom.sub_title.value }}<\/strong><\/p>","title":"{{ page.metafields.custom.header | metafield_tag }}","show_large":false}}},"order":["text_with_media_jNTCBM","17648044152b9d9144","main"]}